indentify/__init__.py
indentify/__main__.py
indentify-0.0.1.dist-info/LICENSE
indentify-0.0.1.dist-info/METADATA
indentify-0.0.1.dist-info/WHEEL
indentify-0.0.1.dist-info/entry_points.txt
indentify-0.0.1.dist-info/top_level.txt
indentify-0.0.1.dist-info/RECORD
